[
  {
    "id": 254,
    "name": "recommend",
    "restaurant_id": 36,
    "created_at": {
      "$date": "2026-05-20T11:01:37.178Z"
    }
  },
  {
    "id": 255,
    "name": "Many people gather together.",
    "restaurant_id": 36,
    "created_at": {
      "$date": "2026-05-20T11:01:39.896Z"
    }
  },
  {
    "id": 256,
    "name": "Double sharing",
    "restaurant_id": 36,
    "created_at": {
      "$date": "2026-05-20T11:01:41.080Z"
    }
  },
  {
    "id": 257,
    "name": "Fried chicken free festival",
    "restaurant_id": 36,
    "created_at": {
      "$date": "2026-05-20T11:01:42.208Z"
    }
  },
  {
    "id": 302,
    "name": "Hamburger and pizza",
    "restaurant_id": 37,
    "created_at": {
      "$date": "2026-05-20T11:04:18.510Z"
    }
  },
  {
    "id": 252,
    "name": "recommend",
    "restaurant_id": 43,
    "created_at": {
      "$date": "2026-05-20T11:01:29.534Z"
    }
  },
  {
    "id": 253,
    "name": "breakfast",
    "restaurant_id": 43,
    "created_at": {
      "$date": "2026-05-20T11:01:33.352Z"
    }
  },
  {
    "id": 258,
    "name": "Special package",
    "restaurant_id": 44,
    "created_at": {
      "$date": "2026-05-20T11:01:44.570Z"
    }
  },
  {
    "id": 259,
    "name": "Hot sale package",
    "restaurant_id": 45,
    "created_at": {
      "$date": "2026-05-20T11:01:51.958Z"
    }
  },
  {
    "id": 260,
    "name": "Multi-person package",
    "restaurant_id": 45,
    "created_at": {
      "$date": "2026-05-20T11:01:55.967Z"
    }
  },
  {
    "id": 261,
    "name": "Signature whole chicken",
    "restaurant_id": 45,
    "created_at": {
      "$date": "2026-05-20T11:01:57.002Z"
    }
  },
  {
    "id": 262,
    "name": "Popular selling",
    "restaurant_id": 46,
    "created_at": {
      "$date": "2026-05-20T11:01:59.785Z"
    }
  },
  {
    "id": 263,
    "name": "Spring is new.",
    "restaurant_id": 46,
    "created_at": {
      "$date": "2026-05-20T11:02:02.088Z"
    }
  },
  {
    "id": 264,
    "name": "hamburg",
    "restaurant_id": 46,
    "created_at": {
      "$date": "2026-05-20T11:02:03.479Z"
    }
  },
  {
    "id": 265,
    "name": "Hamburger snack",
    "restaurant_id": 47,
    "created_at": {
      "$date": "2026-05-20T11:02:06.909Z"
    }
  },
  {
    "id": 266,
    "name": "Hamburger snack",
    "restaurant_id": 48,
    "created_at": {
      "$date": "2026-05-20T11:02:13.874Z"
    }
  },
  {
    "id": 267,
    "name": "China fried chicken",
    "restaurant_id": 48,
    "created_at": {
      "$date": "2026-05-20T11:02:15.132Z"
    }
  },
  {
    "id": 268,
    "name": "Zhengxin chicken cutlet",
    "restaurant_id": 48,
    "created_at": {
      "$date": "2026-05-20T11:02:16.482Z"
    }
  },
  {
    "id": 269,
    "name": "sell well",
    "restaurant_id": 49,
    "created_at": {
      "$date": "2026-05-20T11:02:20.277Z"
    }
  },
  {
    "id": 270,
    "name": "drink",
    "restaurant_id": 50,
    "created_at": {
      "$date": "2026-05-20T11:02:25.144Z"
    }
  },
  {
    "id": 271,
    "name": "drink",
    "restaurant_id": 51,
    "created_at": {
      "$date": "2026-05-20T11:02:31.632Z"
    }
  },
  {
    "id": 272,
    "name": "drink",
    "restaurant_id": 52,
    "created_at": {
      "$date": "2026-05-20T11:02:35.800Z"
    }
  },
  {
    "id": 273,
    "name": "drink",
    "restaurant_id": 53,
    "created_at": {
      "$date": "2026-05-20T11:02:39.251Z"
    }
  },
  {
    "id": 274,
    "name": "drink",
    "restaurant_id": 54,
    "created_at": {
      "$date": "2026-05-20T11:02:42.139Z"
    }
  },
  {
    "id": 275,
    "name": "drink",
    "restaurant_id": 55,
    "created_at": {
      "$date": "2026-05-20T11:02:45.273Z"
    }
  },
  {
    "id": 276,
    "name": "drink",
    "restaurant_id": 56,
    "created_at": {
      "$date": "2026-05-20T11:03:31.798Z"
    }
  },
  {
    "id": 277,
    "name": "Fruits and vegetables yoghourt Xi",
    "restaurant_id": 56,
    "created_at": {
      "$date": "2026-05-20T11:03:32.940Z"
    }
  },
  {
    "id": 278,
    "name": "Only this series",
    "restaurant_id": 57,
    "created_at": {
      "$date": "2026-05-20T11:03:34.898Z"
    }
  },
  {
    "id": 279,
    "name": "recommend",
    "restaurant_id": 57,
    "created_at": {
      "$date": "2026-05-20T11:03:35.571Z"
    }
  },
  {
    "id": 280,
    "name": "Drink something new.",
    "restaurant_id": 58,
    "created_at": {
      "$date": "2026-05-20T11:03:37.361Z"
    }
  },
  {
    "id": 281,
    "name": "recommend",
    "restaurant_id": 58,
    "created_at": {
      "$date": "2026-05-20T11:03:37.903Z"
    }
  },
  {
    "id": 282,
    "name": "fruit",
    "restaurant_id": 59,
    "created_at": {
      "$date": "2026-05-20T11:03:39.760Z"
    }
  },
  {
    "id": 283,
    "name": "Seasonal sales",
    "restaurant_id": 60,
    "created_at": {
      "$date": "2026-05-20T11:03:42.413Z"
    }
  },
  {
    "id": 284,
    "name": "fruit",
    "restaurant_id": 61,
    "created_at": {
      "$date": "2026-05-20T11:03:44.896Z"
    }
  },
  {
    "id": 285,
    "name": "fresh vegetables",
    "restaurant_id": 62,
    "created_at": {
      "$date": "2026-05-20T11:03:47.320Z"
    }
  },
  {
    "id": 286,
    "name": "fresh fruit",
    "restaurant_id": 62,
    "created_at": {
      "$date": "2026-05-20T11:03:47.879Z"
    }
  },
  {
    "id": 287,
    "name": "Jingtiao fruit zhengguo",
    "restaurant_id": 63,
    "created_at": {
      "$date": "2026-05-20T11:03:49.520Z"
    }
  },
  {
    "id": 288,
    "name": "fruit",
    "restaurant_id": 64,
    "created_at": {
      "$date": "2026-05-20T11:03:51.584Z"
    }
  },
  {
    "id": 289,
    "name": "fruit",
    "restaurant_id": 65,
    "created_at": {
      "$date": "2026-05-20T11:03:53.934Z"
    }
  },
  {
    "id": 290,
    "name": "fruit",
    "restaurant_id": 66,
    "created_at": {
      "$date": "2026-05-20T11:03:56.421Z"
    }
  },
  {
    "id": 291,
    "name": "fruit",
    "restaurant_id": 67,
    "created_at": {
      "$date": "2026-05-20T11:03:58.866Z"
    }
  },
  {
    "id": 292,
    "name": "vegetables",
    "restaurant_id": 68,
    "created_at": {
      "$date": "2026-05-20T11:04:00.960Z"
    }
  },
  {
    "id": 293,
    "name": "vegetables",
    "restaurant_id": 69,
    "created_at": {
      "$date": "2026-05-20T11:04:03.399Z"
    }
  },
  {
    "id": 294,
    "name": "vegetables",
    "restaurant_id": 70,
    "created_at": {
      "$date": "2026-05-20T11:04:05.747Z"
    }
  },
  {
    "id": 295,
    "name": "vegetables",
    "restaurant_id": 71,
    "created_at": {
      "$date": "2026-05-20T11:04:08.393Z"
    }
  },
  {
    "id": 296,
    "name": "fruit",
    "restaurant_id": 71,
    "created_at": {
      "$date": "2026-05-20T11:04:09.747Z"
    }
  },
  {
    "id": 297,
    "name": "fruit",
    "restaurant_id": 72,
    "created_at": {
      "$date": "2026-05-20T11:04:10.935Z"
    }
  },
  {
    "id": 298,
    "name": "vegetables",
    "restaurant_id": 73,
    "created_at": {
      "$date": "2026-05-20T11:04:13.191Z"
    }
  },
  {
    "id": 299,
    "name": "fruit",
    "restaurant_id": 73,
    "created_at": {
      "$date": "2026-05-20T11:04:14.560Z"
    }
  },
  {
    "id": 300,
    "name": "pizza",
    "restaurant_id": 74,
    "created_at": {
      "$date": "2026-05-20T11:04:15.850Z"
    }
  },
  {
    "id": 301,
    "name": "Hamburger and pizza",
    "restaurant_id": 74,
    "created_at": {
      "$date": "2026-05-20T11:04:17.187Z"
    }
  },
  {
    "id": 303,
    "name": "Hamburger and pizza",
    "restaurant_id": 75,
    "created_at": {
      "$date": "2026-05-20T11:04:21.136Z"
    }
  },
  {
    "id": 304,
    "name": "Hamburger and pizza",
    "restaurant_id": 76,
    "created_at": {
      "$date": "2026-05-20T11:04:23.500Z"
    }
  },
  {
    "id": 305,
    "name": "fruit",
    "restaurant_id": 77,
    "created_at": {
      "$date": "2026-05-20T11:04:25.944Z"
    }
  },
  {
    "id": 306,
    "name": "vegetables",
    "restaurant_id": 77,
    "created_at": {
      "$date": "2026-05-20T11:04:27.144Z"
    }
  },
  {
    "id": 307,
    "name": "drink",
    "restaurant_id": 78,
    "created_at": {
      "$date": "2026-05-20T11:04:28.496Z"
    }
  },
  {
    "id": 308,
    "name": "ice cream",
    "restaurant_id": 78,
    "created_at": {
      "$date": "2026-05-20T11:04:29.885Z"
    }
  },
  {
    "id": 309,
    "name": "snack",
    "restaurant_id": 79,
    "created_at": {
      "$date": "2026-05-20T11:04:31.006Z"
    }
  },
  {
    "id": 310,
    "name": "drink",
    "restaurant_id": 79,
    "created_at": {
      "$date": "2026-05-20T11:04:32.256Z"
    }
  },
  {
    "id": 311,
    "name": "snack",
    "restaurant_id": 80,
    "created_at": {
      "$date": "2026-05-20T11:04:33.624Z"
    }
  },
  {
    "id": 312,
    "name": "drink",
    "restaurant_id": 80,
    "created_at": {
      "$date": "2026-05-20T11:04:34.154Z"
    }
  },
  {
    "id": 313,
    "name": "drink",
    "restaurant_id": 81,
    "created_at": {
      "$date": "2026-05-20T11:04:35.844Z"
    }
  },
  {
    "id": 314,
    "name": "uble Meal",
    "restaurant_id": 82,
    "created_at": {
      "$date": "2026-05-20T11:04:38.208Z"
    }
  },
  {
    "id": 315,
    "name": "Single-portion meal",
    "restaurant_id": 82,
    "created_at": {
      "$date": "2026-05-20T11:04:38.833Z"
    }
  },
  {
    "id": 316,
    "name": "Four-person meal",
    "restaurant_id": 82,
    "created_at": {
      "$date": "2026-05-20T11:04:39.472Z"
    }
  },
  {
    "id": 317,
    "name": "uble Meal",
    "restaurant_id": 83,
    "created_at": {
      "$date": "2026-05-20T11:04:40.784Z"
    }
  },
  {
    "id": 318,
    "name": "uble Meal",
    "restaurant_id": 84,
    "created_at": {
      "$date": "2026-05-20T11:04:43.392Z"
    }
  },
  {
    "id": 319,
    "name": "uble Meal",
    "restaurant_id": 85,
    "created_at": {
      "$date": "2026-05-20T11:04:45.719Z"
    }
  },
  {
    "id": 320,
    "name": "uble Meal",
    "restaurant_id": 86,
    "created_at": {
      "$date": "2026-05-20T11:04:48.135Z"
    }
  },
  {
    "id": 321,
    "name": "uble Meal",
    "restaurant_id": 87,
    "created_at": {
      "$date": "2026-05-20T11:04:50.686Z"
    }
  },
  {
    "id": 322,
    "name": "uble Meal",
    "restaurant_id": 88,
    "created_at": {
      "$date": "2026-05-20T11:04:53.120Z"
    }
  },
  {
    "id": 323,
    "name": "uble Meal",
    "restaurant_id": 89,
    "created_at": {
      "$date": "2026-05-20T11:04:55.676Z"
    }
  },
  {
    "id": 324,
    "name": "uble Meal",
    "restaurant_id": 90,
    "created_at": {
      "$date": "2026-05-20T11:04:58.035Z"
    }
  },
  {
    "id": 325,
    "name": "uble Meal",
    "restaurant_id": 91,
    "created_at": {
      "$date": "2026-05-20T11:05:00.396Z"
    }
  },
  {
    "id": 326,
    "name": "uble Meal",
    "restaurant_id": 92,
    "created_at": {
      "$date": "2026-05-20T11:05:02.909Z"
    }
  },
  {
    "id": 327,
    "name": "Water",
    "restaurant_id": 93,
    "created_at": {
      "$date": "2026-05-20T11:05:05.268Z"
    }
  },
  {
    "id": 328,
    "name": "Outdoor camping",
    "restaurant_id": 93,
    "created_at": {
      "$date": "2026-05-20T11:05:05.966Z"
    }
  },
  {
    "id": 329,
    "name": "Pet Life",
    "restaurant_id": 93,
    "created_at": {
      "$date": "2026-05-20T11:05:06.478Z"
    }
  },
  {
    "id": 330,
    "name": "chocolate candy",
    "restaurant_id": 94,
    "created_at": {
      "$date": "2026-05-20T11:05:07.731Z"
    }
  },
  {
    "id": 331,
    "name": "Outdoor camping",
    "restaurant_id": 94,
    "created_at": {
      "$date": "2026-05-20T11:05:08.527Z"
    }
  },
  {
    "id": 332,
    "name": "Cool down and seek relief from the heat",
    "restaurant_id": 94,
    "created_at": {
      "$date": "2026-05-20T11:05:09.097Z"
    }
  },
  {
    "id": 333,
    "name": "Cooling essentials",
    "restaurant_id": 95,
    "created_at": {
      "$date": "2026-05-20T11:05:10.256Z"
    }
  },
  {
    "id": 334,
    "name": "Outdoor camping",
    "restaurant_id": 95,
    "created_at": {
      "$date": "2026-05-20T11:05:10.885Z"
    }
  },
  {
    "id": 335,
    "name": "Cooling essentials",
    "restaurant_id": 96,
    "created_at": {
      "$date": "2026-05-20T11:05:12.656Z"
    }
  },
  {
    "id": 336,
    "name": "Personal grooming",
    "restaurant_id": 96,
    "created_at": {
      "$date": "2026-05-20T11:05:13.283Z"
    }
  },
  {
    "id": 337,
    "name": "Recommendation",
    "restaurant_id": 97,
    "created_at": {
      "$date": "2026-05-20T11:05:15.099Z"
    }
  },
  {
    "id": 338,
    "name": "Outdoor camping",
    "restaurant_id": 97,
    "created_at": {
      "$date": "2026-05-20T11:05:15.691Z"
    }
  },
  {
    "id": 339,
    "name": "Recommendation",
    "restaurant_id": 98,
    "created_at": {
      "$date": "2026-05-20T11:05:17.368Z"
    }
  },
  {
    "id": 340,
    "name": "Afternoon tea",
    "restaurant_id": 98,
    "created_at": {
      "$date": "2026-05-20T11:05:17.948Z"
    }
  },
  {
    "id": 341,
    "name": "Recommendation",
    "restaurant_id": 99,
    "created_at": {
      "$date": "2026-05-20T11:05:19.808Z"
    }
  },
  {
    "id": 342,
    "name": "Afternoon tea",
    "restaurant_id": 99,
    "created_at": {
      "$date": "2026-05-20T11:05:20.493Z"
    }
  },
  {
    "id": 343,
    "name": "Recommendation",
    "restaurant_id": 100,
    "created_at": {
      "$date": "2026-05-20T11:05:22.226Z"
    }
  },
  {
    "id": 344,
    "name": "Afternoon tea",
    "restaurant_id": 100,
    "created_at": {
      "$date": "2026-05-20T11:05:22.781Z"
    }
  },
  {
    "id": 345,
    "name": "Afternoon tea",
    "restaurant_id": 101,
    "created_at": {
      "$date": "2026-05-20T11:05:24.672Z"
    }
  },
  {
    "id": 346,
    "name": "food",
    "restaurant_id": 102,
    "created_at": {
      "$date": "2026-05-20T11:05:27.002Z"
    }
  },
  {
    "id": 347,
    "name": "food",
    "restaurant_id": 103,
    "created_at": {
      "$date": "2026-05-20T11:05:29.344Z"
    }
  },
  {
    "id": 348,
    "name": "food",
    "restaurant_id": 104,
    "created_at": {
      "$date": "2026-05-20T11:05:31.895Z"
    }
  },
  {
    "id": 349,
    "name": "food",
    "restaurant_id": 105,
    "created_at": {
      "$date": "2026-05-20T11:05:33.987Z"
    }
  },
  {
    "id": 350,
    "name": "food",
    "restaurant_id": 106,
    "created_at": {
      "$date": "2026-05-20T11:05:36.342Z"
    }
  },
  {
    "id": 351,
    "name": "food",
    "restaurant_id": 107,
    "created_at": {
      "$date": "2026-05-20T11:05:39.160Z"
    }
  },
  {
    "id": 352,
    "name": "food",
    "restaurant_id": 108,
    "created_at": {
      "$date": "2026-05-20T11:05:41.786Z"
    }
  },
  {
    "id": 353,
    "name": "food",
    "restaurant_id": 109,
    "created_at": {
      "$date": "2026-05-20T11:05:44.273Z"
    }
  },
  {
    "id": 354,
    "name": "fruit",
    "restaurant_id": 110,
    "created_at": {
      "$date": "2026-05-20T11:05:46.528Z"
    }
  },
  {
    "id": 355,
    "name": "food",
    "restaurant_id": 110,
    "created_at": {
      "$date": "2026-05-20T11:05:47.144Z"
    }
  }
]
